check_version/__init__.py
check_version/check_version.py
check_version-0.0.2.dist-info/DESCRIPTION.rst
check_version-0.0.2.dist-info/METADATA
check_version-0.0.2.dist-info/RECORD
check_version-0.0.2.dist-info/WHEEL
check_version-0.0.2.dist-info/metadata.json
check_version-0.0.2.dist-info/top_level.txt
